<?xml version="1.0" encoding="utf-8"?>
<Return xmlns="http://www.irs.gov/efile" xmlns:xsi="http://www.w3.org/2001/XMLSchema-instance" xsi:schemaLocation="http://www.irs.gov/efile" returnVersion="2023v6.0">
  <ReturnHeader binaryAttachmentCnt="0">
    <ReturnTs>2025-03-25T11:32:43-05:00</ReturnTs>
    <TaxPeriodEndDt>2024-06-30</TaxPeriodEndDt>
    <PreparerFirmGrp>
      <PreparerFirmEIN>330482495</PreparerFirmEIN>
      <PreparerFirmName>
        <BusinessNameLine1Txt>GYL LLP</BusinessNameLine1Txt>
      </PreparerFirmName>
      <PreparerUSAddress>
        <AddressLine1Txt>4120 CONCOURS SUITE 100</AddressLine1Txt>
        <CityNm>ONTARIO</CityNm>
        <StateAbbreviationCd>CA</StateAbbreviationCd>
        <ZIPCd>91764</ZIPCd>
      </PreparerUSAddress>
    </PreparerFirmGrp>
    <ReturnTypeCd>990</ReturnTypeCd>
    <TaxPeriodBeginDt>2023-07-01</TaxPeriodBeginDt>
    <Filer>
      <EIN>953510046</EIN>
      <BusinessName>
        <BusinessNameLine1Txt>CRYSTAL STAIRS INC</BusinessNameLine1Txt>
      </BusinessName>
      <BusinessNameControlTxt>CRYS</BusinessNameControlTxt>
      <PhoneNum>3232998998</PhoneNum>
      <USAddress>
        <AddressLine1Txt>5110 GOLDLEAF CIRCLE 150</AddressLine1Txt>
        <CityNm>LOS ANGELES</CityNm>
        <StateAbbreviationCd>CA</StateAbbreviationCd>
        <ZIPCd>90056</ZIPCd>
      </USAddress>
    </Filer>
    <BusinessOfficerGrp>
      <PersonNm>JACKIE B MAJORS</PersonNm>
      <PersonTitleTxt>CEO</PersonTitleTxt>
      <PhoneNum>3232998998</PhoneNum>
      <SignatureDt>2025-03-25</SignatureDt>
      <DiscussWithPaidPreparerInd>1</DiscussWithPaidPreparerInd>
    </BusinessOfficerGrp>
    <IRSResponsiblePrtyInfoCurrInd>1</IRSResponsiblePrtyInfoCurrInd>
    <PreparerPersonGrp>
      <PreparerPersonNm>JOSEPH ROMERO CPA</PreparerPersonNm>
      <PTIN>P00441771</PTIN>
      <PhoneNum>9099489990</PhoneNum>
      <SelfEmployedInd>X</SelfEmployedInd>
    </PreparerPersonGrp>
    <TaxYr>2023</TaxYr>
    <BuildTS>2025-03-06 01:10:19Z</BuildTS>
  </ReturnHeader>
  <ReturnData documentCnt="8">
    <IRS990 documentId="RetDoc1038000001" referenceDocumentId="RetDoc1044400001">
      <PrincipalOfficerNm>JACKIE B MAJORS</PrincipalOfficerNm>
      <USAddress>
        <AddressLine1Txt>5110 GOLDLEAF CIRCLE 150</AddressLine1Txt>
        <CityNm>LOS ANGELES</CityNm>
        <StateAbbreviationCd>CA</StateAbbreviationCd>
        <ZIPCd>90056</ZIPCd>
      </USAddress>
      <GrossReceiptsAmt>365538806</GrossReceiptsAmt>
      <GroupReturnForAffiliatesInd>0</GroupReturnForAffiliatesInd>
      <Organization501c3Ind>X</Organization501c3Ind>
      <WebsiteAddressTxt>WWW.CRYSTALSTAIRS.ORG</WebsiteAddressTxt>
      <TypeOfOrganizationCorpInd>X</TypeOfOrganizationCorpInd>
      <FormationYr>1980</FormationYr>
      <LegalDomicileStateCd>CA</LegalDomicileStateCd>
      <ActivityOrMissionDesc>IMPROVING THE LIVES OF FAMILIES THROUGH CHILD CARE SERVICES, RESEARCH AND ADVOCACY</ActivityOrMissionDesc>
      <VotingMembersGoverningBodyCnt>11</VotingMembersGoverningBodyCnt>
      <VotingMembersIndependentCnt>11</VotingMembersIndependentCnt>
      <TotalEmployeeCnt>610</TotalEmployeeCnt>
      <TotalVolunteersCnt>1179</TotalVolunteersCnt>
      <TotalGrossUBIAmt>0</TotalGrossUBIAmt>
      <NetUnrelatedBusTxblIncmAmt>0</NetUnrelatedBusTxblIncmAmt>
      <PYContributionsGrantsAmt>297373690</PYContributionsGrantsAmt>
      <CYContributionsGrantsAmt>364902179</CYContributionsGrantsAmt>
      <PYProgramServiceRevenueAmt>3461</PYProgramServiceRevenueAmt>
      <CYProgramServiceRevenueAmt>65212</CYProgramServiceRevenueAmt>
      <PYInvestmentIncomeAmt>128100</PYInvestmentIncomeAmt>
      <CYInvestmentIncomeAmt>175387</CYInvestmentIncomeAmt>
      <PYOtherRevenueAmt>273596</PYOtherRevenueAmt>
      <CYOtherRevenueAmt>200890</CYOtherRevenueAmt>
      <PYTotalRevenueAmt>297778847</PYTotalRevenueAmt>
      <CYTotalRevenueAmt>365343668</CYTotalRevenueAmt>
      <PYGrantsAndSimilarPaidAmt>0</PYGrantsAndSimilarPaidAmt>
      <CYGrantsAndSimilarPaidAmt>0</CYGrantsAndSimilarPaidAmt>
      <PYBenefitsPaidToMembersAmt>0</PYBenefitsPaidToMembersAmt>
      <CYBenefitsPaidToMembersAmt>0</CYBenefitsPaidToMembersAmt>
      <PYSalariesCompEmpBnftPaidAmt>41495669</PYSalariesCompEmpBnftPaidAmt>
      <CYSalariesCompEmpBnftPaidAmt>43759404</CYSalariesCompEmpBnftPaidAmt>
      <PYTotalProfFndrsngExpnsAmt>0</PYTotalProfFndrsngExpnsAmt>
      <CYTotalProfFndrsngExpnsAmt>0</CYTotalProfFndrsngExpnsAmt>
      <CYTotalFundraisingExpenseAmt>21105</CYTotalFundraisingExpenseAmt>
      <PYOtherExpensesAmt>255481621</PYOtherExpensesAmt>
      <CYOtherExpensesAmt>317183730</CYOtherExpensesAmt>
      <PYTotalExpensesAmt>296977290</PYTotalExpensesAmt>
      <CYTotalExpensesAmt>360943134</CYTotalExpensesAmt>
      <PYRevenuesLessExpensesAmt>801557</PYRevenuesLessExpensesAmt>
      <CYRevenuesLessExpensesAmt>4400534</CYRevenuesLessExpensesAmt>
      <TotalAssetsBOYAmt>89325923</TotalAssetsBOYAmt>
      <TotalAssetsEOYAmt>107208413</TotalAssetsEOYAmt>
      <TotalLiabilitiesBOYAmt>77975205</TotalLiabilitiesBOYAmt>
      <TotalLiabilitiesEOYAmt>91447948</TotalLiabilitiesEOYAmt>
      <NetAssetsOrFundBalancesBOYAmt>11350718</NetAssetsOrFundBalancesBOYAmt>
      <NetAssetsOrFundBalancesEOYAmt>15760465</NetAssetsOrFundBalancesEOYAmt>
      <InfoInScheduleOPartIIIInd>X</InfoInScheduleOPartIIIInd>
      <MissionDesc>IMPROVING THE LIVES OF FAMILIES THROUGH CHILD CARE SERVICES, RESEARCH AND ADVOCACY</MissionDesc>
      <SignificantNewProgramSrvcInd>0</SignificantNewProgramSrvcInd>
      <SignificantChangeInd>0</SignificantChangeInd>
      <ExpenseAmt>237852732</ExpenseAmt>
      <RevenueAmt>293146</RevenueAmt>
      <Desc>CHILD CARE ASSISTANCE PROGRAM - UNDER CONTRACTS WITH THE CALIFORNIA DEPARTMENT OF SOCIAL SERVICES (CDSS) CHILDCARE AND DEVELOPMENT DIVISION, WE ADMINISTER A CHILD CARE PAYMENT PROGRAM FOR LOW-INCOME FAMILIES WHO ARE CYCLING OFF WELFARE (CALWORKS) AS WELL AS THOSE WHO ARE NOT IN THE WELFARE SYSTEM. THE GOAL OF THE PROGRAM IS TO PROMOTE AND SUPPORT FAMILY ECONOMIC SELF-SUFFICIENCY BY PAYING FOR CHILD CARE SO THAT PARENTS CAN WORK, SEEK WORK OR ATTEND SCHOOL/TRAINING. THE PROGRAM ALSO PROVIDES CHILD CARE PAYMENT ASSISTANCE TO FAMILIES REFERRED BY PUBLIC AND PRIVATE AGENCIES BECAUSE THEIR CHILDREN ARE "AT RISK" OF ABUSE OR NEGLECT. WE CERTIFY THE FAMILY'S ELIGIBILITY FOR CHILD CARE, ASSIST THEM TO LOOK FOR AND SELECT CHILD CARE, PROVIDE REFERRALS TO OTHER SUPPORTIVE SERVICES AS NEEDED, AND MAKE MONTHLY PAYMENTS FOR CHILD CARE PROVIDERS THEY SELECT TO CARE FOR THEIR CHILDREN. WE ENROLLED 13,368 FAMILIES WITH A TOTAL OF 22,950 CHILDREN FROM BIRTH TO 12 YEARS OLD, AND MADE MONTHLY PAYMENTS TO 7,667 LICENSED AND LICENSE-EXEMPT CHILD CARE PROVIDERS FOR THEIR SERVICES TO ENROLLED CHILDREN.</Desc>
      <ProgSrvcAccomActy2Grp>
        <ExpenseAmt>77144677</ExpenseAmt>
        <Desc>CALWORKS STAGE 1 CHILD CARE - UNDER A CONTRACT WITH THE LOS ANGELES COUNTY DEPT. OF PUBLIC SOCIAL SERVICES (DPSS), WE ADMINISTER A CHILD CARE PAYMENT PROGRAM FOR CASH-AIDED FAMILIES STARTING THE TRANSITION FROM WELFARE TO WORK. THE GOAL OF THE PROGRAM IS TO PROMOTE A FAMILY'S ECONOMIC SELF-SUFFICIENCY THROUGH EMPLOYMENT AND/OR EDUCATION/TRAINING THAT WILL LEAD TO EMPLOYMENT. WE CERTIFY THE FAMILY'S ELIGIBILITY FOR CHILD CARE, ASSIST THEM TO LOOK FOR AND SELECT CHILD CARE, AND MAKE MONTHLY PAYMENTS FOR SERVICES RENDERED BY CHILD CARE PROVIDERS THEY SELECT TO CARE FOR THEIR CHILDREN. WE ENROLLED 6,379 FAMILIES WITH A TOTAL OF 10,753 CHILDREN FROM BIRTH TO 12 YEARS OLD, AND MADE MONTHLY CHILD CARE PAYMENTS TO 4,790 LICENSED AND LICENSE-EXEMPT CHILD CARE PROVIDERS FOR THEIR SERVICES TO ENROLLED CHILDREN.</Desc>
      </ProgSrvcAccomActy2Grp>
      <ProgSrvcAccomActy3Grp>
        <ExpenseAmt>28693141</ExpenseAmt>
        <Desc>HEAD START AND STATE PRESCHOOL - UNDER THREE GRANTS WITH THE DEPARTMENT OF HEALTH AND HUMAN SERVICES, ADMINISTRATION FOR CHILDREN AND FAMILIES WE ADMINISTER HEAD START, EARLY HEAD START AND CHILD CARE PARTNERSHIP GRANTS FUNDED FOR 1,322 CHILDREN AGES 1 TO 5 YEARS OLD. ALTHOUGH THE PROGRAM WAS UNDER ENROLLED EVERY MONTH IT ACCUMULATIVELY SERVICED 1,549 CHILDREN THIS PAST YEAR. THERE WERE 1,179 VOLUNTEERS EXTENDED LEARNING AT HOME THROUGH THE LEARNING GENIE AND AT THE SITE. SOME COMPLETED IN-PERSON VOLUNTEERING, VOLUNTEERED AT OUR PROGRAM EVENTS, SUPPORTED OUR CHILDREN THROUGH LEARNING AT HOME AND PARTICIPATED IN PARENT ACTIVITIES. OF THOSE CHILDREN ENROLLED, 240 OF THE STUDENTS WERE DUALLY SERVICED IN OUR CALIFORNIA DEPARTMENT OF EDUCATIONS STATE PRESCHOOL PROGRAM WHICH ALLOWS US TO PROVIDE FULL-DAY SERVICES TO WORKING PARENTS AND THOSE WHO ARE IN SCHOOL. THE PROGRAM PROVIDED FULL-DAY SERVICES AT ALL CENTERS FOR 195 DAYS. OF THE CHILDREN AND FAMILIES ENROLLED, 41% HAD ELIGIBILITY AT 100% BELOW FEDERAL POVERTY GUIDELINES; 45% WERE RECEIVING PUBLIC ASSISTANCE (TANIF OR SSI); 5% WERE IN FOSTER CARE; 4% WERE REPORTED AS BEING HOMELESS; AND 5% WERE OVER INCOME. IN ADDITION,10 % OF THOSE CHILDREN HAD AN INDIVIDUALIZED EDUCATION PLAN (IEP) OR INDIVIDUAL FAMILY SERVICES PLAN RECEIVING DISABILITY SERVICES. THE GOAL OF OUR PROGRAM IS TO PROMOTE SCHOOL READINESS BY ENHANCING THE SOCIAL AND COGNITIVE DEVELOPMENT OF THE CHILDREN AND TO SUPPORT FAMILY ENGAGEMENT THAT LEADS TO PARENTS TAKING ON OR MAINTAINING THEIR ROLE AS THE CHILD'S MOST INFLUENTIAL TEACHER. CENTER-BASED SERVICES ARE PROVIDED IN FULL-DAY 8 HOUR SESSIONS. WE TAKE A "HOLISTIC" APPROACH TO SERVING CHILDREN AND THEIR FAMILIES THAT ALLOW US TO SUPPORT THEM IN THE AREAS OF HEALTH, NUTRITION, MENTAL HEALTH AND SOCIAL SERVICES. SERVICES ARE PROVIDED THROUGH OUR STAFF DIRECTLY OR THROUGH A COLLABORATIVE PARTNER. WE HAVE A SHARED GOVERNANCE APPROACH WHERE PARENTS ARE ACTIVELY INVOLVED IN DECISION MAKING.</Desc>
      </ProgSrvcAccomActy3Grp>
      <ProgSrvcAccomActyOtherGrp>
        <ExpenseAmt>6600799</ExpenseAmt>
        <Desc>CHILD CARE RESOURCE AND REFERRALHEALTH OUTREACHCOMMUNITY VOICESCHILD CARE BRIDGE</Desc>
      </ProgSrvcAccomActyOtherGrp>
      <TotalOtherProgSrvcExpenseAmt>6600799</TotalOtherProgSrvcExpenseAmt>
      <TotalProgramServiceExpensesAmt>350291349</TotalProgramServiceExpensesAmt>
      <DescribedInSection501c3Ind referenceDocumentId="RetDoc1039100001">1</DescribedInSection501c3Ind>
      <ScheduleBRequiredInd referenceDocumentId="RetDoc1234500001">1</ScheduleBRequiredInd>
      <PoliticalCampaignActyInd referenceDocumentId="RetDoc1039600001">0</PoliticalCampaignActyInd>
      <LobbyingActivitiesInd referenceDocumentId="RetDoc1039600001">0</LobbyingActivitiesInd>
      <SubjectToProxyTaxInd referenceDocumentId="RetDoc1039600001">0</SubjectToProxyTaxInd>
      <DonorAdvisedFundInd referenceDocumentId="RetDoc1040000001">0</DonorAdvisedFundInd>
      <ConservationEasementsInd referenceDocumentId="RetDoc1040000001">0</ConservationEasementsInd>
      <CollectionsOfArtInd referenceDocumentId="RetDoc1040000001">0</CollectionsOfArtInd>
      <CreditCounselingInd referenceDocumentId="RetDoc1040000001">0</CreditCounselingInd>
      <DonorRstrOrQuasiEndowmentsInd>0</DonorRstrOrQuasiEndowmentsInd>
      <ReportLandBuildingEquipmentInd referenceDocumentId="RetDoc1040000001">1</ReportLandBuildingEquipmentInd>
      <ReportInvestmentsOtherSecInd referenceDocumentId="RetDoc1040000001">0</ReportInvestmentsOtherSecInd>
      <ReportProgramRelatedInvstInd referenceDocumentId="RetDoc1040000001">0</ReportProgramRelatedInvstInd>
      <ReportOtherAssetsInd referenceDocumentId="RetDoc1040000001">1</ReportOtherAssetsInd>
      <ReportOtherLiabilitiesInd referenceDocumentId="RetDoc1040000001">1</ReportOtherLiabilitiesInd>
      <IncludeFIN48FootnoteInd referenceDocumentId="RetDoc1040000001">1</IncludeFIN48FootnoteInd>
      <IndependentAuditFinclStmtInd referenceDocumentId="RetDoc1040000001">1</IndependentAuditFinclStmtInd>
      <ConsolidatedAuditFinclStmtInd referenceDocumentId="RetDoc1040000001">0</ConsolidatedAuditFinclStmtInd>
      <SchoolOperatingInd>0</SchoolOperatingInd>
      <ForeignOfficeInd>0</ForeignOfficeInd>
      <ForeignActivitiesInd>0</ForeignActivitiesInd>
      <MoreThan5000KToOrgInd>0</MoreThan5000KToOrgInd>
      <MoreThan5000KToIndividualsInd>0</MoreThan5000KToIndividualsInd>
      <ProfessionalFundraisingInd referenceDocumentId="RetDoc1041300001">0</ProfessionalFundraisingInd>
      <FundraisingActivitiesInd referenceDocumentId="RetDoc1041300001">1</FundraisingActivitiesInd>
      <GamingActivitiesInd referenceDocumentId="RetDoc1041300001">0</GamingActivitiesInd>
      <OperateHospitalInd>0</OperateHospitalInd>
      <GrantsToOrganizationsInd>0</GrantsToOrganizationsInd>
      <GrantsToIndividualsInd>0</GrantsToIndividualsInd>
      <ScheduleJRequiredInd referenceDocumentId="RetDoc1042400001">1</ScheduleJRequiredInd>
      <TaxExemptBondsInd>0</TaxExemptBondsInd>
      <EngagedInExcessBenefitTransInd>0</EngagedInExcessBenefitTransInd>
      <PYExcessBenefitTransInd>0</PYExcessBenefitTransInd>
      <LoanOutstandingInd>0</LoanOutstandingInd>
      <GrantToRelatedPersonInd>0</GrantToRelatedPersonInd>
      <BusinessRlnWithOrgMemInd>0</BusinessRlnWithOrgMemInd>
      <BusinessRlnWithFamMemInd>0</BusinessRlnWithFamMemInd>
      <BusinessRlnWith35CtrlEntInd>0</BusinessRlnWith35CtrlEntInd>
      <DeductibleNonCashContriInd>0</DeductibleNonCashContriInd>
      <DeductibleArtContributionInd>0</DeductibleArtContributionInd>
      <TerminateOperationsInd>0</TerminateOperationsInd>
      <PartialLiquidationInd>0</PartialLiquidationInd>
      <DisregardedEntityInd>0</DisregardedEntityInd>
      <RelatedEntityInd>0</RelatedEntityInd>
      <RelatedOrganizationCtrlEntInd>0</RelatedOrganizationCtrlEntInd>
      <TrnsfrExmptNonChrtblRltdOrgInd>0</TrnsfrExmptNonChrtblRltdOrgInd>
      <ActivitiesConductedPrtshpInd>0</ActivitiesConductedPrtshpInd>
      <ScheduleORequiredInd>1</ScheduleORequiredInd>
      <IRPDocumentCnt>9788</IRPDocumentCnt>
      <IRPDocumentW2GCnt>0</IRPDocumentW2GCnt>
      <BackupWthldComplianceInd>1</BackupWthldComplianceInd>
      <EmployeeCnt>610</EmployeeCnt>
      <EmploymentTaxReturnsFiledInd>1</EmploymentTaxReturnsFiledInd>
      <UnrelatedBusIncmOverLimitInd>0</UnrelatedBusIncmOverLimitInd>
      <ForeignFinancialAccountInd>0</ForeignFinancialAccountInd>
      <ProhibitedTaxShelterTransInd>0</ProhibitedTaxShelterTransInd>
      <TaxablePartyNotificationInd>0</TaxablePartyNotificationInd>
      <NondeductibleContributionsInd>0</NondeductibleContributionsInd>
      <QuidProQuoContributionsInd>0</QuidProQuoContributionsInd>
      <Form8282PropertyDisposedOfInd>0</Form8282PropertyDisposedOfInd>
      <RcvFndsToPayPrsnlBnftCntrctInd>0</RcvFndsToPayPrsnlBnftCntrctInd>
      <PayPremiumsPrsnlBnftCntrctInd>0</PayPremiumsPrsnlBnftCntrctInd>
      <IndoorTanningServicesInd>0</IndoorTanningServicesInd>
      <SubjToTaxRmnrtnExPrchtPymtInd>0</SubjToTaxRmnrtnExPrchtPymtInd>
      <SubjectToExcsTaxNetInvstIncInd>0</SubjectToExcsTaxNetInvstIncInd>
      <InfoInScheduleOPartVIInd>X</InfoInScheduleOPartVIInd>
      <GoverningBodyVotingMembersCnt>11</GoverningBodyVotingMembersCnt>
      <IndependentVotingMemberCnt>11</IndependentVotingMemberCnt>
      <FamilyOrBusinessRlnInd>0</FamilyOrBusinessRlnInd>
      <DelegationOfMgmtDutiesInd>0</DelegationOfMgmtDutiesInd>
      <ChangeToOrgDocumentsInd>0</ChangeToOrgDocumentsInd>
      <MaterialDiversionOrMisuseInd>0</MaterialDiversionOrMisuseInd>
      <MembersOrStockholdersInd>0</MembersOrStockholdersInd>
      <ElectionOfBoardMembersInd>0</ElectionOfBoardMembersInd>
      <DecisionsSubjectToApprovaInd>0</DecisionsSubjectToApprovaInd>
      <MinutesOfGoverningBodyInd>1</MinutesOfGoverningBodyInd>
      <MinutesOfCommitteesInd>1</MinutesOfCommitteesInd>
      <OfficerMailingAddressInd>0</OfficerMailingAddressInd>
      <LocalChaptersInd>0</LocalChaptersInd>
      <Form990ProvidedToGvrnBodyInd>1</Form990ProvidedToGvrnBodyInd>
      <ConflictOfInterestPolicyInd>1</ConflictOfInterestPolicyInd>
      <AnnualDisclosureCoveredPrsnInd>1</AnnualDisclosureCoveredPrsnInd>
      <RegularMonitoringEnfrcInd>1</RegularMonitoringEnfrcInd>
      <WhistleblowerPolicyInd>1</WhistleblowerPolicyInd>
      <DocumentRetentionPolicyInd>1</DocumentRetentionPolicyInd>
      <CompensationProcessCEOInd>1</CompensationProcessCEOInd>
      <CompensationProcessOtherInd>1</CompensationProcessOtherInd>
      <InvestmentInJointVentureInd>0</InvestmentInJointVentureInd>
      <StatesWhereCopyOfReturnIsFldCd>CA</StatesWhereCopyOfReturnIsFldCd>
      <OtherWebsiteInd>X</OtherWebsiteInd>
      <UponRequestInd>X</UponRequestInd>
      <BooksInCareOfDetail>
        <PersonNm>LY TANYA G LOUGHRIDGE CFO</PersonNm>
        <PhoneNum>3234211408</PhoneNum>
        <USAddress>
          <AddressLine1Txt>5110 W GOLDLEAF CIRCLE SUITE 150</AddressLine1Txt>
          <CityNm>LOS ANGELES</CityNm>
          <StateAbbreviationCd>CA</StateAbbreviationCd>
          <ZIPCd>900561282</ZIPCd>
        </USAddress>
      </BooksInCareOfDetail>
      <Form990PartVIISectionAGrp>
        <PersonNm>HEIDI ROTH</PersonNm>
        <TitleTxt>BOARD CHAIR</TitleTxt>
        <AverageHoursPerWeekRt>1.00</AverageHoursPerWeekRt>
        <IndividualTrusteeOrDirectorInd>X</IndividualTrusteeOrDirectorInd>
        <OfficerInd>X</OfficerInd>
        <ReportableCompFromOrgAmt>0</ReportableCompFromOrgAmt>
        <ReportableCompFromRltdOrgAmt>0</ReportableCompFromRltdOrgAmt>
        <OtherCompensationAmt>0</OtherCompensationAmt>
      </Form990PartVIISectionAGrp>
      <Form990PartVIISectionAGrp>
        <PersonNm>REAGAN FEENEY</PersonNm>
        <TitleTxt>BOARD MEMBER</TitleTxt>
        <AverageHoursPerWeekRt>1.00</AverageHoursPerWeekRt>
        <IndividualTrusteeOrDirectorInd>X</IndividualTrusteeOrDirectorInd>
        <ReportableCompFromOrgAmt>0</ReportableCompFromOrgAmt>
        <ReportableCompFromRltdOrgAmt>0</ReportableCompFromRltdOrgAmt>
        <OtherCompensationAmt>0</OtherCompensationAmt>
      </Form990PartVIISectionAGrp>
      <Form990PartVIISectionAGrp>
        <PersonNm>JOHN COLEMAN</PersonNm>
        <TitleTxt>VICE CHAIR/TREASURER</TitleTxt>
        <AverageHoursPerWeekRt>1.00</AverageHoursPerWeekRt>
        <IndividualTrusteeOrDirectorInd>X</IndividualTrusteeOrDirectorInd>
        <OfficerInd>X</OfficerInd>
        <ReportableCompFromOrgAmt>0</ReportableCompFromOrgAmt>
        <ReportableCompFromRltdOrgAmt>0</ReportableCompFromRltdOrgAmt>
        <OtherCompensationAmt>0</OtherCompensationAmt>
      </Form990PartVIISectionAGrp>
      <Form990PartVIISectionAGrp>
        <PersonNm>AMBER FINCH</PersonNm>
        <TitleTxt>BOARD SECRETARY</TitleTxt>
        <AverageHoursPerWeekRt>1.00</AverageHoursPerWeekRt>
        <IndividualTrusteeOrDirectorInd>X</IndividualTrusteeOrDirectorInd>
        <ReportableCompFromOrgAmt>0</ReportableCompFromOrgAmt>
        <ReportableCompFromRltdOrgAmt>0</ReportableCompFromRltdOrgAmt>
        <OtherCompensationAmt>0</OtherCompensationAmt>
      </Form990PartVIISectionAGrp>
      <Form990PartVIISectionAGrp>
        <PersonNm>VICTOR LEE</PersonNm>
        <TitleTxt>PAST BOARD MEMBER</TitleTxt>
        <AverageHoursPerWeekRt>1.00</AverageHoursPerWeekRt>
        <IndividualTrusteeOrDirectorInd>X</IndividualTrusteeOrDirectorInd>
        <ReportableCompFromOrgAmt>0</ReportableCompFromOrgAmt>
        <ReportableCompFromRltdOrgAmt>0</ReportableCompFromRltdOrgAmt>
        <OtherCompensationAmt>0</OtherCompensationAmt>
      </Form990PartVIISectionAGrp>
      <Form990PartVIISectionAGrp>
        <PersonNm>ALECIA WINFIELD</PersonNm>
        <TitleTxt>BOARD MEMBER</TitleTxt>
        <AverageHoursPerWeekRt>1.00</AverageHoursPerWeekRt>
        <IndividualTrusteeOrDirectorInd>X</IndividualTrusteeOrDirectorInd>
        <ReportableCompFromOrgAmt>0</ReportableCompFromOrgAmt>
        <ReportableCompFromRltdOrgAmt>0</ReportableCompFromRltdOrgAmt>
        <OtherCompensationAmt>0</OtherCompensationAmt>
      </Form990PartVIISectionAGrp>
      <Form990PartVIISectionAGrp>
        <PersonNm>MICHAEL THOMAS</PersonNm>
        <TitleTxt>BOARD MEMBER</TitleTxt>
        <AverageHoursPerWeekRt>1.00</AverageHoursPerWeekRt>
        <IndividualTrusteeOrDirectorInd>X</IndividualTrusteeOrDirectorInd>
        <ReportableCompFromOrgAmt>0</ReportableCompFromOrgAmt>
        <ReportableCompFromRltdOrgAmt>0</ReportableCompFromRltdOrgAmt>
        <OtherCompensationAmt>0</OtherCompensationAmt>
      </Form990PartVIISectionAGrp>
      <Form990PartVIISectionAGrp>
        <PersonNm>LESLIE KELLEY</PersonNm>
        <TitleTxt>BOARD MEMBER</TitleTxt>
        <AverageHoursPerWeekRt>1.00</AverageHoursPerWeekRt>
        <IndividualTrusteeOrDirectorInd>X</IndividualTrusteeOrDirectorInd>
        <ReportableCompFromOrgAmt>0</ReportableCompFromOrgAmt>
        <ReportableCompFromRltdOrgAmt>0</ReportableCompFromRltdOrgAmt>
        <OtherCompensationAmt>0</OtherCompensationAmt>
      </Form990PartVIISectionAGrp>
      <Form990PartVIISectionAGrp>
        <PersonNm>STEPHEN ROBERTS</PersonNm>
        <TitleTxt>BOARD MEMBER</TitleTxt>
        <AverageHoursPerWeekRt>1.00</AverageHoursPerWeekRt>
        <IndividualTrusteeOrDirectorInd>X</IndividualTrusteeOrDirectorInd>
        <ReportableCompFromOrgAmt>0</ReportableCompFromOrgAmt>
        <ReportableCompFromRltdOrgAmt>0</ReportableCompFromRltdOrgAmt>
        <OtherCompensationAmt>0</OtherCompensationAmt>
      </Form990PartVIISectionAGrp>
      <Form990PartVIISectionAGrp>
        <PersonNm>MICHELLE QUAN</PersonNm>
        <TitleTxt>BOARD MEMBER</TitleTxt>
        <AverageHoursPerWeekRt>1.00</AverageHoursPerWeekRt>
        <IndividualTrusteeOrDirectorInd>X</IndividualTrusteeOrDirectorInd>
        <ReportableCompFromOrgAmt>0</ReportableCompFromOrgAmt>
        <ReportableCompFromRltdOrgAmt>0</ReportableCompFromRltdOrgAmt>
        <OtherCompensationAmt>0</OtherCompensationAmt>
      </Form990PartVIISectionAGrp>
      <Form990PartVIISectionAGrp>
        <PersonNm>NDIDI UKA</PersonNm>
        <TitleTxt>BOARD MEMBER</TitleTxt>
        <AverageHoursPerWeekRt>1.00</AverageHoursPerWeekRt>
        <IndividualTrusteeOrDirectorInd>X</IndividualTrusteeOrDirectorInd>
        <ReportableCompFromOrgAmt>0</ReportableCompFromOrgAmt>
        <ReportableCompFromRltdOrgAmt>0</ReportableCompFromRltdOrgAmt>
        <OtherCompensationAmt>0</OtherCompensationAmt>
      </Form990PartVIISectionAGrp>
      <Form990PartVIISectionAGrp>
        <PersonNm>LENISE YARBER</PersonNm>
        <TitleTxt>BOARD MEMBER</TitleTxt>
        <AverageHoursPerWeekRt>1.00</AverageHoursPerWeekRt>
        <IndividualTrusteeOrDirectorInd>X</IndividualTrusteeOrDirectorInd>
        <ReportableCompFromOrgAmt>0</ReportableCompFromOrgAmt>
        <ReportableCompFromRltdOrgAmt>0</ReportableCompFromRltdOrgAmt>
        <OtherCompensationAmt>0</OtherCompensationAmt>
      </Form990PartVIISectionAGrp>
      <Form990PartVIISectionAGrp>
        <PersonNm>JACKIE MAJORS</PersonNm>
        <TitleTxt>CEO</TitleTxt>
        <AverageHoursPerWeekRt>40.00</AverageHoursPerWeekRt>
        <OfficerInd>X</OfficerInd>
        <ReportableCompFromOrgAmt>443830</ReportableCompFromOrgAmt>
        <ReportableCompFromRltdOrgAmt>0</ReportableCompFromRltdOrgAmt>
        <OtherCompensationAmt>20533</OtherCompensationAmt>
      </Form990PartVIISectionAGrp>
      <Form990PartVIISectionAGrp>
        <PersonNm>KENDALL HIRAI</PersonNm>
        <TitleTxt>COO</TitleTxt>
        <AverageHoursPerWeekRt>40.00</AverageHoursPerWeekRt>
        <OfficerInd>X</OfficerInd>
        <ReportableCompFromOrgAmt>277396</ReportableCompFromOrgAmt>
        <ReportableCompFromRltdOrgAmt>0</ReportableCompFromRltdOrgAmt>
        <OtherCompensationAmt>23553</OtherCompensationAmt>
      </Form990PartVIISectionAGrp>
      <Form990PartVIISectionAGrp>
        <PersonNm>LY TANYA G LOUGHRIDGE</PersonNm>
        <TitleTxt>CFO</TitleTxt>
        <AverageHoursPerWeekRt>40.00</AverageHoursPerWeekRt>
        <OfficerInd>X</OfficerInd>
        <ReportableCompFromOrgAmt>257673</ReportableCompFromOrgAmt>
        <ReportableCompFromRltdOrgAmt>0</ReportableCompFromRltdOrgAmt>
        <OtherCompensationAmt>30252</OtherCompensationAmt>
      </Form990PartVIISectionAGrp>
      <Form990PartVIISectionAGrp>
        <PersonNm>LAURA CARDENAS</PersonNm>
        <TitleTxt>HS DIRECTOR</TitleTxt>
        <AverageHoursPerWeekRt>40.00</AverageHoursPerWeekRt>
        <HighestCompensatedEmployeeInd>X</HighestCompensatedEmployeeInd>
        <ReportableCompFromOrgAmt>137286</ReportableCompFromOrgAmt>
        <ReportableCompFromRltdOrgAmt>0</ReportableCompFromRltdOrgAmt>
        <OtherCompensationAmt>31716</OtherCompensationAmt>
      </Form990PartVIISectionAGrp>
      <Form990PartVIISectionAGrp>
        <PersonNm>ILEANA SARAFIAN</PersonNm>
        <TitleTxt>DIRECTOR OF EXTERNAL AFFAIRS</TitleTxt>
        <AverageHoursPerWeekRt>40.00</AverageHoursPerWeekRt>
        <HighestCompensatedEmployeeInd>X</HighestCompensatedEmployeeInd>
        <ReportableCompFromOrgAmt>128218</ReportableCompFromOrgAmt>
        <ReportableCompFromRltdOrgAmt>0</ReportableCompFromRltdOrgAmt>
        <OtherCompensationAmt>13915</OtherCompensationAmt>
      </Form990PartVIISectionAGrp>
      <Form990PartVIISectionAGrp>
        <PersonNm>LISA D MORRIS</PersonNm>
        <TitleTxt>CHIEF COMPLIANCE OFFICER AND GENERAL COUNSEL</TitleTxt>
        <AverageHoursPerWeekRt>40.00</AverageHoursPerWeekRt>
        <HighestCompensatedEmployeeInd>X</HighestCompensatedEmployeeInd>
        <ReportableCompFromOrgAmt>203819</ReportableCompFromOrgAmt>
        <ReportableCompFromRltdOrgAmt>0</ReportableCompFromRltdOrgAmt>
        <OtherCompensationAmt>34900</OtherCompensationAmt>
      </Form990PartVIISectionAGrp>
      <Form990PartVIISectionAGrp>
        <PersonNm>SINTHIA ARUYA</PersonNm>
        <TitleTxt>SENIOR DIRECTOR, HUMAN RESOURCES</TitleTxt>
        <AverageHoursPerWeekRt>1.00</AverageHoursPerWeekRt>
        <HighestCompensatedEmployeeInd>X</HighestCompensatedEmployeeInd>
        <ReportableCompFromOrgAmt>157978</ReportableCompFromOrgAmt>
        <ReportableCompFromRltdOrgAmt>0</ReportableCompFromRltdOrgAmt>
        <OtherCompensationAmt>34756</OtherCompensationAmt>
      </Form990PartVIISectionAGrp>
      <Form990PartVIISectionAGrp>
        <PersonNm>LASHONNA GRANT</PersonNm>
        <TitleTxt>HS ASSISTANT DIRECTOR</TitleTxt>
        <AverageHoursPerWeekRt>1.00</AverageHoursPerWeekRt>
        <HighestCompensatedEmployeeInd>X</HighestCompensatedEmployeeInd>
        <ReportableCompFromOrgAmt>115377</ReportableCompFromOrgAmt>
        <ReportableCompFromRltdOrgAmt>0</ReportableCompFromRltdOrgAmt>
        <OtherCompensationAmt>15272</OtherCompensationAmt>
      </Form990PartVIISectionAGrp>
      <TotalReportableCompFromOrgAmt>1721577</TotalReportableCompFromOrgAmt>
      <TotReportableCompRltdOrgAmt>0</TotReportableCompRltdOrgAmt>
      <TotalOtherCompensationAmt>204897</TotalOtherCompensationAmt>
      <IndivRcvdGreaterThan100KCnt>9</IndivRcvdGreaterThan100KCnt>
      <FormerOfcrEmployeesListedInd>0</FormerOfcrEmployeesListedInd>
      <TotalCompGreaterThan150KInd>1</TotalCompGreaterThan150KInd>
      <CompensationFromOtherSrcsInd>0</CompensationFromOtherSrcsInd>
      <ContractorCompensationGrp>
        <ContractorName>
          <BusinessName>
            <BusinessNameLine1Txt>BUCKNER FOUNDATION</BusinessNameLine1Txt>
          </BusinessName>
        </ContractorName>
        <ContractorAddress>
          <USAddress>
            <AddressLine1Txt>2330 W FLORENCE AVENUE</AddressLine1Txt>
            <CityNm>LOS ANGELES</CityNm>
            <StateAbbreviationCd>CA</StateAbbreviationCd>
            <ZIPCd>900435145</ZIPCd>
          </USAddress>
        </ContractorAddress>
        <ServicesDesc>CHILDCARE SERVICES</ServicesDesc>
        <CompensationAmt>2225475</CompensationAmt>
      </ContractorCompensationGrp>
      <ContractorCompensationGrp>
        <ContractorName>
          <BusinessName>
            <BusinessNameLine1Txt>A BRIGHT BEGINNING</BusinessNameLine1Txt>
          </BusinessName>
        </ContractorName>
        <ContractorAddress>
          <USAddress>
            <AddressLine1Txt>712 E MANCHESTER BOULEVARD</AddressLine1Txt>
            <CityNm>INGLEWOOD</CityNm>
            <StateAbbreviationCd>CA</StateAbbreviationCd>
            <ZIPCd>903011912</ZIPCd>
          </USAddress>
        </ContractorAddress>
        <ServicesDesc>CHILDCARE SERVICES</ServicesDesc>
        <CompensationAmt>1812627</CompensationAmt>
      </ContractorCompensationGrp>
      <ContractorCompensationGrp>
        <ContractorName>
          <BusinessName>
            <BusinessNameLine1Txt>CHARVON Y JONES</BusinessNameLine1Txt>
          </BusinessName>
        </ContractorName>
        <ContractorAddress>
          <USAddress>
            <AddressLine1Txt>1415 CENTINELA AVENUE</AddressLine1Txt>
            <CityNm>INGLEWOOD</CityNm>
            <StateAbbreviationCd>CA</StateAbbreviationCd>
            <ZIPCd>903021141</ZIPCd>
          </USAddress>
        </ContractorAddress>
        <ServicesDesc>CHILDCARE SERVICES</ServicesDesc>
        <CompensationAmt>1570691</CompensationAmt>
      </ContractorCompensationGrp>
      <ContractorCompensationGrp>
        <ContractorName>
          <BusinessName>
            <BusinessNameLine1Txt>CREATIVE LEARNING ACADEMY INC</BusinessNameLine1Txt>
          </BusinessName>
        </ContractorName>
        <ContractorAddress>
          <USAddress>
            <AddressLine1Txt>3060 AVIANO COURT</AddressLine1Txt>
            <CityNm>CHINIO HILLS</CityNm>
            <StateAbbreviationCd>CA</StateAbbreviationCd>
            <ZIPCd>917096658</ZIPCd>
          </USAddress>
        </ContractorAddress>
        <ServicesDesc>CHILDCARE SERVICES</ServicesDesc>
        <CompensationAmt>1559006</CompensationAmt>
      </ContractorCompensationGrp>
      <ContractorCompensationGrp>
        <ContractorName>
          <BusinessName>
            <BusinessNameLine1Txt>YMCA OF GREATER LONG BEACH</BusinessNameLine1Txt>
          </BusinessName>
        </ContractorName>
        <ContractorAddress>
          <USAddress>
            <AddressLine1Txt>5835 CARSON ST</AddressLine1Txt>
            <CityNm>LAKEWOOD</CityNm>
            <StateAbbreviationCd>CA</StateAbbreviationCd>
            <ZIPCd>907133056</ZIPCd>
          </USAddress>
        </ContractorAddress>
        <ServicesDesc>CHILDCARE SERVICES</ServicesDesc>
        <CompensationAmt>1482274</CompensationAmt>
      </ContractorCompensationGrp>
      <CntrctRcvdGreaterThan100KCnt>516</CntrctRcvdGreaterThan100KCnt>
      <FundraisingAmt>109431</FundraisingAmt>
      <GovernmentGrantsAmt>326943209</GovernmentGrantsAmt>
      <AllOtherContributionsAmt>37849539</AllOtherContributionsAmt>
      <TotalContributionsAmt>364902179</TotalContributionsAmt>
      <ProgramServiceRevenueGrp>
        <Desc>PARENT FEES</Desc>
        <BusinessCd>624110</BusinessCd>
        <TotalRevenueColumnAmt>57906</TotalRevenueColumnAmt>
        <RelatedOrExemptFuncIncomeAmt>57906</RelatedOrExemptFuncIncomeAmt>
      </ProgramServiceRevenueGrp>
      <ProgramServiceRevenueGrp>
        <Desc>PROGRAM FEES</Desc>
        <BusinessCd>624410</BusinessCd>
        <TotalRevenueColumnAmt>7306</TotalRevenueColumnAmt>
        <RelatedOrExemptFuncIncomeAmt>7306</RelatedOrExemptFuncIncomeAmt>
      </ProgramServiceRevenueGrp>
      <TotalProgramServiceRevenueAmt>65212</TotalProgramServiceRevenueAmt>
      <InvestmentIncomeGrp>
        <TotalRevenueColumnAmt>157237</TotalRevenueColumnAmt>
        <ExclusionAmt>157237</ExclusionAmt>
      </InvestmentIncomeGrp>
      <GrossAmountSalesAssetsGrp>
        <SecuritiesAmt>160100</SecuritiesAmt>
      </GrossAmountSalesAssetsGrp>
      <LessCostOthBasisSalesExpnssGrp>
        <SecuritiesAmt>141950</SecuritiesAmt>
      </LessCostOthBasisSalesExpnssGrp>
      <GainOrLossGrp>
        <SecuritiesAmt>18150</SecuritiesAmt>
      </GainOrLossGrp>
      <NetGainOrLossInvestmentsGrp>
        <TotalRevenueColumnAmt>18150</TotalRevenueColumnAmt>
        <ExclusionAmt>18150</ExclusionAmt>
      </NetGainOrLossInvestmentsGrp>
      <FundraisingGrossIncomeAmt>26144</FundraisingGrossIncomeAmt>
      <ContriRptFundraisingEventAmt>109431</ContriRptFundraisingEventAmt>
      <FundraisingDirectExpensesAmt>53188</FundraisingDirectExpensesAmt>
      <NetIncmFromFundraisingEvtGrp>
        <TotalRevenueColumnAmt>-27044</TotalRevenueColumnAmt>
        <ExclusionAmt>-27044</ExclusionAmt>
      </NetIncmFromFundraisingEvtGrp>
      <OtherRevenueMiscGrp>
        <Desc>OTHER CHILD CARE INCOME</Desc>
        <BusinessCd>624410</BusinessCd>
        <TotalRevenueColumnAmt>227934</TotalRevenueColumnAmt>
        <RelatedOrExemptFuncIncomeAmt>227934</RelatedOrExemptFuncIncomeAmt>
      </OtherRevenueMiscGrp>
      <OtherRevenueTotalAmt>227934</OtherRevenueTotalAmt>
      <TotalRevenueGrp>
        <TotalRevenueColumnAmt>365343668</TotalRevenueColumnAmt>
        <RelatedOrExemptFuncIncomeAmt>293146</RelatedOrExemptFuncIncomeAmt>
        <UnrelatedBusinessRevenueAmt>0</UnrelatedBusinessRevenueAmt>
        <ExclusionAmt>148343</ExclusionAmt>
      </TotalRevenueGrp>
      <CompCurrentOfcrDirectorsGrp>
        <TotalAmt>1097817</TotalAmt>
        <ManagementAndGeneralAmt>1097817</ManagementAndGeneralAmt>
      </CompCurrentOfcrDirectorsGrp>
      <OtherSalariesAndWagesGrp>
        <TotalAmt>33016395</TotalAmt>
        <ProgramServicesAmt>28246140</ProgramServicesAmt>
        <ManagementAndGeneralAmt>4770255</ManagementAndGeneralAmt>
      </OtherSalariesAndWagesGrp>
      <PensionPlanContributionsGrp>
        <TotalAmt>1238899</TotalAmt>
        <ProgramServicesAmt>1015897</ProgramServicesAmt>
        <ManagementAndGeneralAmt>223002</ManagementAndGeneralAmt>
      </PensionPlanContributionsGrp>
      <OtherEmployeeBenefitsGrp>
        <TotalAmt>5803339</TotalAmt>
        <ProgramServicesAmt>5273320</ProgramServicesAmt>
        <ManagementAndGeneralAmt>530019</ManagementAndGeneralAmt>
      </OtherEmployeeBenefitsGrp>
      <PayrollTaxesGrp>
        <TotalAmt>2602954</TotalAmt>
        <ProgramServicesAmt>2160830</ProgramServicesAmt>
        <ManagementAndGeneralAmt>442124</ManagementAndGeneralAmt>
      </PayrollTaxesGrp>
      <FeesForServicesLegalGrp>
        <TotalAmt>192957</TotalAmt>
        <ManagementAndGeneralAmt>192957</ManagementAndGeneralAmt>
      </FeesForServicesLegalGrp>
      <FeesForServicesAccountingGrp>
        <TotalAmt>113316</TotalAmt>
        <ManagementAndGeneralAmt>113316</ManagementAndGeneralAmt>
      </FeesForServicesAccountingGrp>
      <OfficeExpensesGrp>
        <TotalAmt>2619741</TotalAmt>
        <ProgramServicesAmt>2216880</ProgramServicesAmt>
        <ManagementAndGeneralAmt>402861</ManagementAndGeneralAmt>
      </OfficeExpensesGrp>
      <InformationTechnologyGrp>
        <TotalAmt>960430</TotalAmt>
        <ProgramServicesAmt>605081</ProgramServicesAmt>
        <ManagementAndGeneralAmt>355349</ManagementAndGeneralAmt>
      </InformationTechnologyGrp>
      <OccupancyGrp>
        <TotalAmt>7494451</TotalAmt>
        <ProgramServicesAmt>6098649</ProgramServicesAmt>
        <ManagementAndGeneralAmt>1395802</ManagementAndGeneralAmt>
      </OccupancyGrp>
      <TravelGrp>
        <TotalAmt>172867</TotalAmt>
        <ProgramServicesAmt>157579</ProgramServicesAmt>
        <ManagementAndGeneralAmt>15288</ManagementAndGeneralAmt>
      </TravelGrp>
      <ConferencesMeetingsGrp>
        <TotalAmt>391269</TotalAmt>
        <ProgramServicesAmt>326150</ProgramServicesAmt>
        <ManagementAndGeneralAmt>65119</ManagementAndGeneralAmt>
      </ConferencesMeetingsGrp>
      <DepreciationDepletionGrp>
        <TotalAmt>939612</TotalAmt>
        <ProgramServicesAmt>939104</ProgramServicesAmt>
        <ManagementAndGeneralAmt>508</ManagementAndGeneralAmt>
      </DepreciationDepletionGrp>
      <InsuranceGrp>
        <TotalAmt>457546</TotalAmt>
        <ProgramServicesAmt>316293</ProgramServicesAmt>
        <ManagementAndGeneralAmt>141253</ManagementAndGeneralAmt>
      </InsuranceGrp>
      <OtherExpensesGrp>
        <Desc>PROVIDER PAYMENTS</Desc>
        <TotalAmt>299842055</TotalAmt>
        <ProgramServicesAmt>299842055</ProgramServicesAmt>
      </OtherExpensesGrp>
      <OtherExpensesGrp>
        <Desc>FOOD SUPPLIES</Desc>
        <TotalAmt>1261935</TotalAmt>
        <ProgramServicesAmt>1261935</ProgramServicesAmt>
      </OtherExpensesGrp>
      <OtherExpensesGrp>
        <Desc>OTHER SERVICES AND EXP</Desc>
        <TotalAmt>1226263</TotalAmt>
        <ProgramServicesAmt>988756</ProgramServicesAmt>
        <ManagementAndGeneralAmt>237507</ManagementAndGeneralAmt>
      </OtherExpensesGrp>
      <OtherExpensesGrp>
        <Desc>MISCELLANEOUS</Desc>
        <TotalAmt>784986</TotalAmt>
        <ProgramServicesAmt>137483</ProgramServicesAmt>
        <ManagementAndGeneralAmt>647503</ManagementAndGeneralAmt>
      </OtherExpensesGrp>
      <AllOtherExpensesGrp>
        <TotalAmt>726302</TotalAmt>
        <ProgramServicesAmt>705197</ProgramServicesAmt>
        <FundraisingAmt>21105</FundraisingAmt>
      </AllOtherExpensesGrp>
      <TotalFunctionalExpensesGrp>
        <TotalAmt>360943134</TotalAmt>
        <ProgramServicesAmt>350291349</ProgramServicesAmt>
        <ManagementAndGeneralAmt>10630680</ManagementAndGeneralAmt>
        <FundraisingAmt>21105</FundraisingAmt>
      </TotalFunctionalExpensesGrp>
      <CashNonInterestBearingGrp>
        <BOYAmt>100</BOYAmt>
        <EOYAmt>100</EOYAmt>
      </CashNonInterestBearingGrp>
      <SavingsAndTempCashInvstGrp>
        <BOYAmt>15897501</BOYAmt>
        <EOYAmt>27796489</EOYAmt>
      </SavingsAndTempCashInvstGrp>
      <PledgesAndGrantsReceivableGrp>
        <BOYAmt>35965999</BOYAmt>
        <EOYAmt>39673963</EOYAmt>
      </PledgesAndGrantsReceivableGrp>
      <AccountsReceivableGrp>
        <BOYAmt>2590095</BOYAmt>
        <EOYAmt>2440029</EOYAmt>
      </AccountsReceivableGrp>
      <PrepaidExpensesDefrdChargesGrp>
        <BOYAmt>581693</BOYAmt>
        <EOYAmt>505228</EOYAmt>
      </PrepaidExpensesDefrdChargesGrp>
      <LandBldgEquipCostOrOtherBssAmt>18878061</LandBldgEquipCostOrOtherBssAmt>
      <LandBldgEquipAccumDeprecAmt>7521925</LandBldgEquipAccumDeprecAmt>
      <LandBldgEquipBasisNetGrp>
        <BOYAmt>7111955</BOYAmt>
        <EOYAmt>11356136</EOYAmt>
      </LandBldgEquipBasisNetGrp>
      <InvestmentsPubTradedSecGrp>
        <BOYAmt>2739327</BOYAmt>
        <EOYAmt>2876063</EOYAmt>
      </InvestmentsPubTradedSecGrp>
      <OtherAssetsTotalGrp>
        <BOYAmt>24439253</BOYAmt>
        <EOYAmt>22560405</EOYAmt>
      </OtherAssetsTotalGrp>
      <TotalAssetsGrp>
        <BOYAmt>89325923</BOYAmt>
        <EOYAmt>107208413</EOYAmt>
      </TotalAssetsGrp>
      <AccountsPayableAccrExpnssGrp>
        <BOYAmt>29286337</BOYAmt>
        <EOYAmt>41334388</EOYAmt>
      </AccountsPayableAccrExpnssGrp>
      <GrantsPayableGrp>
        <BOYAmt>5789778</BOYAmt>
        <EOYAmt>13097213</EOYAmt>
      </GrantsPayableGrp>
      <DeferredRevenueGrp>
        <BOYAmt>12575393</BOYAmt>
        <EOYAmt>6201593</EOYAmt>
      </DeferredRevenueGrp>
      <OtherLiabilitiesGrp>
        <BOYAmt>30323697</BOYAmt>
        <EOYAmt>30814754</EOYAmt>
      </OtherLiabilitiesGrp>
      <TotalLiabilitiesGrp>
        <BOYAmt>77975205</BOYAmt>
        <EOYAmt>91447948</EOYAmt>
      </TotalLiabilitiesGrp>
      <OrganizationFollowsFASB117Ind>X</OrganizationFollowsFASB117Ind>
      <NoDonorRestrictionNetAssetsGrp>
        <BOYAmt>11350718</BOYAmt>
        <EOYAmt>15760465</EOYAmt>
      </NoDonorRestrictionNetAssetsGrp>
      <TotalNetAssetsFundBalanceGrp>
        <BOYAmt>11350718</BOYAmt>
        <EOYAmt>15760465</EOYAmt>
      </TotalNetAssetsFundBalanceGrp>
      <TotLiabNetAssetsFundBalanceGrp>
        <BOYAmt>89325923</BOYAmt>
        <EOYAmt>107208413</EOYAmt>
      </TotLiabNetAssetsFundBalanceGrp>
      <InfoInScheduleOPartXIInd>X</InfoInScheduleOPartXIInd>
      <ReconcilationRevenueExpnssAmt>4400534</ReconcilationRevenueExpnssAmt>
      <NetUnrlzdGainsLossesInvstAmt>118644</NetUnrlzdGainsLossesInvstAmt>
      <DonatedServicesAndUseFcltsAmt>100282</DonatedServicesAndUseFcltsAmt>
      <OtherChangesInNetAssetsAmt>-209713</OtherChangesInNetAssetsAmt>
      <MethodOfAccountingAccrualInd>X</MethodOfAccountingAccrualInd>
      <AccountantCompileOrReviewInd>0</AccountantCompileOrReviewInd>
      <FSAuditedInd>1</FSAuditedInd>
      <FSAuditedBasisGrp>
        <SeparateBasisFinclStmtInd>X</SeparateBasisFinclStmtInd>
      </FSAuditedBasisGrp>
      <AuditCommitteeInd>1</AuditCommitteeInd>
      <FederalGrantAuditRequiredInd>1</FederalGrantAuditRequiredInd>
      <FederalGrantAuditPerformedInd>1</FederalGrantAuditPerformedInd>
    </IRS990>
    <IRS990ScheduleA documentId="RetDoc1039100001">
      <PublicOrganization170Ind>X</PublicOrganization170Ind>
      <GiftsGrantsContriRcvd170Grp>
        <CurrentTaxYearMinus4YearsAmt>215036168</CurrentTaxYearMinus4YearsAmt>
        <CurrentTaxYearMinus3YearsAmt>245072180</CurrentTaxYearMinus3YearsAmt>
        <CurrentTaxYearMinus2YearsAmt>252412057</CurrentTaxYearMinus2YearsAmt>
        <CurrentTaxYearMinus1YearAmt>297373690</CurrentTaxYearMinus1YearAmt>
        <CurrentTaxYearAmt>364902179</CurrentTaxYearAmt>
        <TotalAmt>1374796274</TotalAmt>
      </GiftsGrantsContriRcvd170Grp>
      <TotalCalendarYear170Grp>
        <CurrentTaxYearMinus4YearsAmt>215036168</CurrentTaxYearMinus4YearsAmt>
        <CurrentTaxYearMinus3YearsAmt>245072180</CurrentTaxYearMinus3YearsAmt>
        <CurrentTaxYearMinus2YearsAmt>252412057</CurrentTaxYearMinus2YearsAmt>
        <CurrentTaxYearMinus1YearAmt>297373690</CurrentTaxYearMinus1YearAmt>
        <CurrentTaxYearAmt>364902179</CurrentTaxYearAmt>
        <TotalAmt>1374796274</TotalAmt>
      </TotalCalendarYear170Grp>
      <PublicSupportTotal170Amt>1374796274</PublicSupportTotal170Amt>
      <GrossInvestmentIncome170Grp>
        <CurrentTaxYearMinus4YearsAmt>37653</CurrentTaxYearMinus4YearsAmt>
        <CurrentTaxYearMinus3YearsAmt>41760</CurrentTaxYearMinus3YearsAmt>
        <CurrentTaxYearMinus2YearsAmt>87338</CurrentTaxYearMinus2YearsAmt>
        <CurrentTaxYearMinus1YearAmt>115448</CurrentTaxYearMinus1YearAmt>
        <CurrentTaxYearAmt>157237</CurrentTaxYearAmt>
        <TotalAmt>439436</TotalAmt>
      </GrossInvestmentIncome170Grp>
      <OtherIncome170Grp>
        <CurrentTaxYearMinus4YearsAmt>149854</CurrentTaxYearMinus4YearsAmt>
        <CurrentTaxYearMinus3YearsAmt>136969</CurrentTaxYearMinus3YearsAmt>
        <CurrentTaxYearMinus2YearsAmt>211693</CurrentTaxYearMinus2YearsAmt>
        <CurrentTaxYearMinus1YearAmt>273596</CurrentTaxYearMinus1YearAmt>
        <CurrentTaxYearAmt>26144</CurrentTaxYearAmt>
        <TotalAmt>798256</TotalAmt>
      </OtherIncome170Grp>
      <TotalSupportAmt>1376033966</TotalSupportAmt>
      <GrossReceiptsRltdActivitiesAmt>6118596</GrossReceiptsRltdActivitiesAmt>
      <PublicSupportCY170Pct>0.99910</PublicSupportCY170Pct>
      <PublicSupportPY170Pct>0.99880</PublicSupportPY170Pct>
      <ThirtyThrPctSuprtTestsCY170Ind>X</ThirtyThrPctSuprtTestsCY170Ind>
    </IRS990ScheduleA>
    <IRS990ScheduleB documentId="RetDoc1234500001">
      <ContributorInformationGrp>
        <ContributorNum>RESTRICTED</ContributorNum>
        <ContributorBusinessName>
          <BusinessNameLine1>RESTRICTED</BusinessNameLine1>
        </ContributorBusinessName>
        <ContributorUSAddress>
          <AddressLine1>RESTRICTED</AddressLine1>
          <AddressLine2>RESTRICTED</AddressLine2>
          <City>RESTRICTED</City>
          <State>RESTRICTED</State>
          <ZIPCode>RESTRICTED</ZIPCode>
        </ContributorUSAddress>
        <TotalContributionsAmt>RESTRICTED</TotalContributionsAmt>
      </ContributorInformationGrp>
    </IRS990ScheduleB>
    <IRS990ScheduleC documentId="RetDoc1039600001">
      <AvgLobbyingNontaxableAmountGrp>
        <CurrentYearMinus3Amt>1000000</CurrentYearMinus3Amt>
        <TotalAmt>1000000</TotalAmt>
      </AvgLobbyingNontaxableAmountGrp>
      <LobbyingCeilingAmt>1500000</LobbyingCeilingAmt>
      <AvgTotalLobbyingExpendGrp>
        <CurrentYearMinus3Amt>131</CurrentYearMinus3Amt>
        <TotalAmt>131</TotalAmt>
      </AvgTotalLobbyingExpendGrp>
      <AvgGrassrootsNontaxableGrp>
        <CurrentYearMinus3Amt>250000</CurrentYearMinus3Amt>
        <TotalAmt>250000</TotalAmt>
      </AvgGrassrootsNontaxableGrp>
      <GrassrootsCeilingAmt>375000</GrassrootsCeilingAmt>
    </IRS990ScheduleC>
    <IRS990ScheduleD documentId="RetDoc1040000001">
      <LandGrp>
        <OtherCostOrOtherBasisAmt>4404020</OtherCostOrOtherBasisAmt>
        <BookValueAmt>4404020</BookValueAmt>
      </LandGrp>
      <BuildingsGrp>
        <OtherCostOrOtherBasisAmt>1498178</OtherCostOrOtherBasisAmt>
        <DepreciationAmt>76830</DepreciationAmt>
        <BookValueAmt>1421348</BookValueAmt>
      </BuildingsGrp>
      <LeaseholdImprovementsGrp>
        <OtherCostOrOtherBasisAmt>2093696</OtherCostOrOtherBasisAmt>
        <DepreciationAmt>874793</DepreciationAmt>
        <BookValueAmt>1218903</BookValueAmt>
      </LeaseholdImprovementsGrp>
      <EquipmentGrp>
        <OtherCostOrOtherBasisAmt>10882167</OtherCostOrOtherBasisAmt>
        <DepreciationAmt>6570302</DepreciationAmt>
        <BookValueAmt>4311865</BookValueAmt>
      </EquipmentGrp>
      <TotalBookValueLandBuildingsAmt>11356136</TotalBookValueLandBuildingsAmt>
      <OtherAssetsOrgGrp>
        <Desc>DEPOSITS</Desc>
        <BookValueAmt>372775</BookValueAmt>
      </OtherAssetsOrgGrp>
      <OtherAssetsOrgGrp>
        <Desc>RIGHT-OF-USE ASSETS, OPERATING LEASES</Desc>
        <BookValueAmt>22187630</BookValueAmt>
      </OtherAssetsOrgGrp>
      <TotalBookValueOtherAssetsAmt>22560405</TotalBookValueOtherAssetsAmt>
      <OtherLiabilitiesOrgGrp>
        <Desc>CDE RESERVE</Desc>
        <Amt>3758863</Amt>
      </OtherLiabilitiesOrgGrp>
      <OtherLiabilitiesOrgGrp>
        <Desc>OTHER LIABILITIES</Desc>
        <Amt>332340</Amt>
      </OtherLiabilitiesOrgGrp>
      <OtherLiabilitiesOrgGrp>
        <Desc>OPERATING LEASE LIABILITIES</Desc>
        <Amt>26723551</Amt>
      </OtherLiabilitiesOrgGrp>
      <TotalLiabilityAmt>30814754</TotalLiabilityAmt>
      <FootnoteTextInd>X</FootnoteTextInd>
      <TotalRevEtcAuditedFinclStmtAmt>365506351</TotalRevEtcAuditedFinclStmtAmt>
      <NetUnrealizedGainsInvstAmt>118644</NetUnrealizedGainsInvstAmt>
      <DonatedServicesAndUseFcltsAmt>100282</DonatedServicesAndUseFcltsAmt>
      <OtherRevenueAmt>53188</OtherRevenueAmt>
      <RevenueNotReportedAmt>272114</RevenueNotReportedAmt>
      <RevenueSubtotalAmt>365234237</RevenueSubtotalAmt>
      <OtherRevenuesNotIncludedAmt>109431</OtherRevenuesNotIncludedAmt>
      <RevenueNotReportedFinclStmtAmt>109431</RevenueNotReportedFinclStmtAmt>
      <TotalRevenuePerForm990Amt>365343668</TotalRevenuePerForm990Amt>
      <TotExpnsEtcAuditedFinclStmtAmt>361096604</TotExpnsEtcAuditedFinclStmtAmt>
      <DonatedServicesUseFcltsAmt>100282</DonatedServicesUseFcltsAmt>
      <OtherExpensesIncludedAmt>53188</OtherExpensesIncludedAmt>
      <ExpensesNotReportedAmt>153470</ExpensesNotReportedAmt>
      <ExpensesSubtotalAmt>360943134</ExpensesSubtotalAmt>
      <ExpensesNotRptFinclStmtAmt>0</ExpensesNotRptFinclStmtAmt>
      <TotalExpensesPerForm990Amt>360943134</TotalExpensesPerForm990Amt>
      <SupplementalInformationDetail>
        <FormAndLineReferenceDesc>PART X, LINE 2:</FormAndLineReferenceDesc>
        <ExplanationTxt>GENERALLY ACCEPTED ACCOUNTING PRINCIPLES PROVIDE ACCOUNTING AND DISCLOSURE GUIDANCE ABOUT POSITIONS TAKEN BY AN ORGANIZATION IN ITS TAX RETURNS THAT MIGHT BE UNCERTAIN. MANAGEMENT HAS CONSIDERED ITS TAX POSITIONS AND BELIEVES THAT ALL OF THE POSITIONS TAKEN BY THE ORGANIZATION IN ITS FEDERAL AND STATE EXEMPT ORGANIZATION TAX RETURNS ARE MORE LIKELY THAN NOT TO BE SUSTAINED UPON EXAMINATION. THE ORGANIZATION'S RETURNS ARE SUBJECT TO EXAMINATION BY FEDERAL AND STATE TAXING AUTHORITIES, GENERALLY FOR FOUR YEARS AFTER THEY ARE FILED.</ExplanationTxt>
      </SupplementalInformationDetail>
      <SupplementalInformationDetail>
        <FormAndLineReferenceDesc>PART XI, LINE 2D - OTHER ADJUSTMENTS:</FormAndLineReferenceDesc>
        <ExplanationTxt>FUNDRAISING 53,188.</ExplanationTxt>
      </SupplementalInformationDetail>
      <SupplementalInformationDetail>
        <FormAndLineReferenceDesc>PART XI, LINE 4B - OTHER ADJUSTMENTS:</FormAndLineReferenceDesc>
        <ExplanationTxt>FUNDRAISING INCOME 109,431.</ExplanationTxt>
      </SupplementalInformationDetail>
      <SupplementalInformationDetail>
        <FormAndLineReferenceDesc>PART XII, LINE 2D - OTHER ADJUSTMENTS:</FormAndLineReferenceDesc>
        <ExplanationTxt>FUNDRAISING EXPENSES 53,188.</ExplanationTxt>
      </SupplementalInformationDetail>
    </IRS990ScheduleD>
    <IRS990ScheduleG documentId="RetDoc1041300001">
      <FundraisingEventInformationGrp>
        <Event1Nm>DINNER</Event1Nm>
        <GrossReceiptsEvent1Amt>135575</GrossReceiptsEvent1Amt>
        <CharitableContriEvent1Amt>109431</CharitableContriEvent1Amt>
        <GrossRevenueEvent1Amt>26144</GrossRevenueEvent1Amt>
        <RentFacilityCostsEvent1Amt>9389</RentFacilityCostsEvent1Amt>
        <FoodAndBeverageEvent1Amt>31220</FoodAndBeverageEvent1Amt>
        <EntertainmentEvent1Amt>6300</EntertainmentEvent1Amt>
        <OtherDirectExpensesEvent1Amt>6279</OtherDirectExpensesEvent1Amt>
        <GrossReceiptsTotalAmt>135575</GrossReceiptsTotalAmt>
        <CharitableContributionsTotAmt>109431</CharitableContributionsTotAmt>
        <GrossRevenueTotalEventsAmt>26144</GrossRevenueTotalEventsAmt>
        <RentFcltyCostsTotalEventsAmt>9389</RentFcltyCostsTotalEventsAmt>
        <FoodAndBeverageTotalEventsAmt>31220</FoodAndBeverageTotalEventsAmt>
        <EntertainmentTotalEventsAmt>6300</EntertainmentTotalEventsAmt>
        <OthDirectExpnssTotalEventsAmt>6279</OthDirectExpnssTotalEventsAmt>
        <DirectExpenseSummaryEventsAmt>53188</DirectExpenseSummaryEventsAmt>
        <NetIncomeSummaryAmt>-27044</NetIncomeSummaryAmt>
      </FundraisingEventInformationGrp>
    </IRS990ScheduleG>
    <IRS990ScheduleJ documentId="RetDoc1042400001">
      <CompensationSurveyInd>X</CompensationSurveyInd>
      <BoardOrCommitteeApprovalInd>X</BoardOrCommitteeApprovalInd>
      <SeverancePaymentInd>0</SeverancePaymentInd>
      <SupplementalNonqualRtrPlanInd>0</SupplementalNonqualRtrPlanInd>
      <EquityBasedCompArrngmInd>0</EquityBasedCompArrngmInd>
      <CompBasedOnRevenueOfFlngOrgInd>0</CompBasedOnRevenueOfFlngOrgInd>
      <CompBsdOnRevRelatedOrgsInd>0</CompBsdOnRevRelatedOrgsInd>
      <CompBsdNetEarnsFlngOrgInd>0</CompBsdNetEarnsFlngOrgInd>
      <CompBsdNetEarnsRltdOrgsInd>0</CompBsdNetEarnsRltdOrgsInd>
      <AnyNonFixedPaymentsInd>0</AnyNonFixedPaymentsInd>
      <InitialContractExceptionInd>0</InitialContractExceptionInd>
      <RltdOrgOfficerTrstKeyEmplGrp>
        <PersonNm>JACKIE MAJORS</PersonNm>
        <TitleTxt>CEO</TitleTxt>
        <BaseCompensationFilingOrgAmt>443830</BaseCompensationFilingOrgAmt>
        <CompensationBasedOnRltdOrgsAmt>0</CompensationBasedOnRltdOrgsAmt>
        <BonusFilingOrganizationAmount>0</BonusFilingOrganizationAmount>
        <BonusRelatedOrganizationsAmt>0</BonusRelatedOrganizationsAmt>
        <OtherCompensationFilingOrgAmt>0</OtherCompensationFilingOrgAmt>
        <OtherCompensationRltdOrgsAmt>0</OtherCompensationRltdOrgsAmt>
        <DeferredCompensationFlngOrgAmt>0</DeferredCompensationFlngOrgAmt>
        <DeferredCompRltdOrgsAmt>0</DeferredCompRltdOrgsAmt>
        <NontaxableBenefitsFilingOrgAmt>20533</NontaxableBenefitsFilingOrgAmt>
        <NontaxableBenefitsRltdOrgsAmt>0</NontaxableBenefitsRltdOrgsAmt>
        <TotalCompensationFilingOrgAmt>464363</TotalCompensationFilingOrgAmt>
        <TotalCompensationRltdOrgsAmt>0</TotalCompensationRltdOrgsAmt>
        <CompReportPrior990FilingOrgAmt>0</CompReportPrior990FilingOrgAmt>
        <CompReportPrior990RltdOrgsAmt>0</CompReportPrior990RltdOrgsAmt>
      </RltdOrgOfficerTrstKeyEmplGrp>
      <RltdOrgOfficerTrstKeyEmplGrp>
        <PersonNm>KENDALL HIRAI</PersonNm>
        <TitleTxt>COO</TitleTxt>
        <BaseCompensationFilingOrgAmt>277396</BaseCompensationFilingOrgAmt>
        <CompensationBasedOnRltdOrgsAmt>0</CompensationBasedOnRltdOrgsAmt>
        <BonusFilingOrganizationAmount>0</BonusFilingOrganizationAmount>
        <BonusRelatedOrganizationsAmt>0</BonusRelatedOrganizationsAmt>
        <OtherCompensationFilingOrgAmt>0</OtherCompensationFilingOrgAmt>
        <OtherCompensationRltdOrgsAmt>0</OtherCompensationRltdOrgsAmt>
        <DeferredCompensationFlngOrgAmt>0</DeferredCompensationFlngOrgAmt>
        <DeferredCompRltdOrgsAmt>0</DeferredCompRltdOrgsAmt>
        <NontaxableBenefitsFilingOrgAmt>23553</NontaxableBenefitsFilingOrgAmt>
        <NontaxableBenefitsRltdOrgsAmt>0</NontaxableBenefitsRltdOrgsAmt>
        <TotalCompensationFilingOrgAmt>300949</TotalCompensationFilingOrgAmt>
        <TotalCompensationRltdOrgsAmt>0</TotalCompensationRltdOrgsAmt>
        <CompReportPrior990FilingOrgAmt>0</CompReportPrior990FilingOrgAmt>
        <CompReportPrior990RltdOrgsAmt>0</CompReportPrior990RltdOrgsAmt>
      </RltdOrgOfficerTrstKeyEmplGrp>
      <RltdOrgOfficerTrstKeyEmplGrp>
        <PersonNm>LY TANYA G LOUGHRIDGE</PersonNm>
        <TitleTxt>CFO</TitleTxt>
        <BaseCompensationFilingOrgAmt>257673</BaseCompensationFilingOrgAmt>
        <CompensationBasedOnRltdOrgsAmt>0</CompensationBasedOnRltdOrgsAmt>
        <BonusFilingOrganizationAmount>0</BonusFilingOrganizationAmount>
        <BonusRelatedOrganizationsAmt>0</BonusRelatedOrganizationsAmt>
        <OtherCompensationFilingOrgAmt>0</OtherCompensationFilingOrgAmt>
        <OtherCompensationRltdOrgsAmt>0</OtherCompensationRltdOrgsAmt>
        <DeferredCompensationFlngOrgAmt>0</DeferredCompensationFlngOrgAmt>
        <DeferredCompRltdOrgsAmt>0</DeferredCompRltdOrgsAmt>
        <NontaxableBenefitsFilingOrgAmt>30252</NontaxableBenefitsFilingOrgAmt>
        <NontaxableBenefitsRltdOrgsAmt>0</NontaxableBenefitsRltdOrgsAmt>
        <TotalCompensationFilingOrgAmt>287925</TotalCompensationFilingOrgAmt>
        <TotalCompensationRltdOrgsAmt>0</TotalCompensationRltdOrgsAmt>
        <CompReportPrior990FilingOrgAmt>0</CompReportPrior990FilingOrgAmt>
        <CompReportPrior990RltdOrgsAmt>0</CompReportPrior990RltdOrgsAmt>
      </RltdOrgOfficerTrstKeyEmplGrp>
      <RltdOrgOfficerTrstKeyEmplGrp>
        <PersonNm>LISA D MORRIS</PersonNm>
        <TitleTxt>CHIEF COMPLIANCE OFFICER AND GENERAL</TitleTxt>
        <BaseCompensationFilingOrgAmt>203819</BaseCompensationFilingOrgAmt>
        <CompensationBasedOnRltdOrgsAmt>0</CompensationBasedOnRltdOrgsAmt>
        <BonusFilingOrganizationAmount>0</BonusFilingOrganizationAmount>
        <BonusRelatedOrganizationsAmt>0</BonusRelatedOrganizationsAmt>
        <OtherCompensationFilingOrgAmt>0</OtherCompensationFilingOrgAmt>
        <OtherCompensationRltdOrgsAmt>0</OtherCompensationRltdOrgsAmt>
        <DeferredCompensationFlngOrgAmt>0</DeferredCompensationFlngOrgAmt>
        <DeferredCompRltdOrgsAmt>0</DeferredCompRltdOrgsAmt>
        <NontaxableBenefitsFilingOrgAmt>34900</NontaxableBenefitsFilingOrgAmt>
        <NontaxableBenefitsRltdOrgsAmt>0</NontaxableBenefitsRltdOrgsAmt>
        <TotalCompensationFilingOrgAmt>238719</TotalCompensationFilingOrgAmt>
        <TotalCompensationRltdOrgsAmt>0</TotalCompensationRltdOrgsAmt>
        <CompReportPrior990FilingOrgAmt>0</CompReportPrior990FilingOrgAmt>
        <CompReportPrior990RltdOrgsAmt>0</CompReportPrior990RltdOrgsAmt>
      </RltdOrgOfficerTrstKeyEmplGrp>
      <RltdOrgOfficerTrstKeyEmplGrp>
        <PersonNm>SINTHIA ARUYA</PersonNm>
        <TitleTxt>SENIOR DIRECTOR, HUMAN RESOURCES</TitleTxt>
        <BaseCompensationFilingOrgAmt>157978</BaseCompensationFilingOrgAmt>
        <CompensationBasedOnRltdOrgsAmt>0</CompensationBasedOnRltdOrgsAmt>
        <BonusFilingOrganizationAmount>0</BonusFilingOrganizationAmount>
        <BonusRelatedOrganizationsAmt>0</BonusRelatedOrganizationsAmt>
        <OtherCompensationFilingOrgAmt>0</OtherCompensationFilingOrgAmt>
        <OtherCompensationRltdOrgsAmt>0</OtherCompensationRltdOrgsAmt>
        <DeferredCompensationFlngOrgAmt>0</DeferredCompensationFlngOrgAmt>
        <DeferredCompRltdOrgsAmt>0</DeferredCompRltdOrgsAmt>
        <NontaxableBenefitsFilingOrgAmt>34756</NontaxableBenefitsFilingOrgAmt>
        <NontaxableBenefitsRltdOrgsAmt>0</NontaxableBenefitsRltdOrgsAmt>
        <TotalCompensationFilingOrgAmt>192734</TotalCompensationFilingOrgAmt>
        <TotalCompensationRltdOrgsAmt>0</TotalCompensationRltdOrgsAmt>
        <CompReportPrior990FilingOrgAmt>0</CompReportPrior990FilingOrgAmt>
        <CompReportPrior990RltdOrgsAmt>0</CompReportPrior990RltdOrgsAmt>
      </RltdOrgOfficerTrstKeyEmplGrp>
      <RltdOrgOfficerTrstKeyEmplGrp>
        <PersonNm>LAURA CARDENAS</PersonNm>
        <TitleTxt>HS DIRECTOR</TitleTxt>
        <BaseCompensationFilingOrgAmt>137286</BaseCompensationFilingOrgAmt>
        <CompensationBasedOnRltdOrgsAmt>0</CompensationBasedOnRltdOrgsAmt>
        <BonusFilingOrganizationAmount>0</BonusFilingOrganizationAmount>
        <BonusRelatedOrganizationsAmt>0</BonusRelatedOrganizationsAmt>
        <OtherCompensationFilingOrgAmt>0</OtherCompensationFilingOrgAmt>
        <OtherCompensationRltdOrgsAmt>0</OtherCompensationRltdOrgsAmt>
        <DeferredCompensationFlngOrgAmt>0</DeferredCompensationFlngOrgAmt>
        <DeferredCompRltdOrgsAmt>0</DeferredCompRltdOrgsAmt>
        <NontaxableBenefitsFilingOrgAmt>31716</NontaxableBenefitsFilingOrgAmt>
        <NontaxableBenefitsRltdOrgsAmt>0</NontaxableBenefitsRltdOrgsAmt>
        <TotalCompensationFilingOrgAmt>169002</TotalCompensationFilingOrgAmt>
        <TotalCompensationRltdOrgsAmt>0</TotalCompensationRltdOrgsAmt>
        <CompReportPrior990FilingOrgAmt>0</CompReportPrior990FilingOrgAmt>
        <CompReportPrior990RltdOrgsAmt>0</CompReportPrior990RltdOrgsAmt>
      </RltdOrgOfficerTrstKeyEmplGrp>
    </IRS990ScheduleJ>
    <IRS990ScheduleO documentId="RetDoc1044400001">
      <SupplementalInformationDetail>
        <FormAndLineReferenceDesc>FORM 990, PART VI, SECTION B, LINE 11B</FormAndLineReferenceDesc>
        <ExplanationTxt>THE FORM 990 IS REVIEWED INTERNALLY BY THE FINANCE STAFF THEN FORWARDED TO THE AUDIT COMMITTEE OF THE BOARD OF DIRECTORS FOR REVIEW. THE AUDIT COMMITTEE PRESENTS THE FORM 990 TO ALL BOARD MEMBERS FOR APPROVAL BEFORE FILING.</ExplanationTxt>
      </SupplementalInformationDetail>
      <SupplementalInformationDetail>
        <FormAndLineReferenceDesc>FORM 990, PART VI, SECTION B, LINE 12C</FormAndLineReferenceDesc>
        <ExplanationTxt>CONFLICT OF INTEREST STATEMENTS ARE REVIEWED ANNUALLY BY THE AUDIT COMMITTEE CHAIR AND CHIEF COMPLIANCE OFFICER AND GENERAL COUNSEL. ALSO, THE ORGANIZATION HAS PROTOCOLS FOR ADDRESSING POTENTIAL CONFLICT OF INTEREST ISSUES AS WELL AS A REPORTING PROCESS.</ExplanationTxt>
      </SupplementalInformationDetail>
      <SupplementalInformationDetail>
        <FormAndLineReferenceDesc>FORM 990, PART VI, SECTION B, LINE 15</FormAndLineReferenceDesc>
        <ExplanationTxt>EACH YEAR THE PERSONNEL COMMITTEE AND THEN THE BOARD FOLLOWS THE IRS REBUTTABLE PRESCRIPTION PROCESS FOR THE C-SUITE OFFICERS BASED ON COMPARABILITY DATA. SAID REVIEW OCCURS BEFORE THE COMPENSATION APPROVED IS PAID. BOARD APPROVAL OF CALENDAR YEAR 2023 COMPENSATION OCCURRED IN DECEMBER OF 2022.</ExplanationTxt>
      </SupplementalInformationDetail>
      <SupplementalInformationDetail>
        <FormAndLineReferenceDesc>FORM 990, PART VI, SECTION C, LINE 19</FormAndLineReferenceDesc>
        <ExplanationTxt>THESE DOCUMENTS ARE MADE AVAILABLE UPON REQUEST.</ExplanationTxt>
      </SupplementalInformationDetail>
      <SupplementalInformationDetail>
        <FormAndLineReferenceDesc>FORM 990, PART XI, LINE 9:</FormAndLineReferenceDesc>
        <ExplanationTxt>OFFSET FOR DONATED SERVICES -100,282. FUNDRAISING INCOME -109,431.</ExplanationTxt>
      </SupplementalInformationDetail>
    </IRS990ScheduleO>
  </ReturnData>
</Return>